[
  {
    "chunk_id": "5c31cb75-c53e-4445-86c0-057bd5c9a4fc",
    "video_id": "Att8P0C40FU",
    "channel_id": "",
    "channel_name": "Dry Creek Wrangler School",
    "title": "Heartbreak and Loss",
    "text": "afternoon Dwayne here Dry Creek Wrangler School um the last video I put up was the one I was at the airport waiting for Mama and I was sitting in the truck and I talked about the three-legged dog and chasing things that gets you in trouble and learning to eventually quit chasing those things and I got a and on videos before that I've gotten a lot of questions a lot of folks want me to address a heartbreak and heartache um now I want to say here I want to stop here and say here I know that I get a lot of emails sent to me asking for counsel and asking for advice on certain things I read all the emails um but I don't I don't answer them okay and I don't want those who have reached out and sent emails asking for Counsel on certain things I don't want you to think I don't read them and I don't want you to think that I don't care because I haven't answered and I don't answer probably not going to answer the reasons I I just feel like I need to share this there's two reasons why I don't answer them number one I'm not a therapist I I'm just a dude I'm just a guy who's kind of been through some stuff who raised kids who kind of points out some things and just tries to kind of help with General Direction in life when it comes to individual counsel there's people out there that are way more qualified than I am and when a question comes to me a few sentences on a page I don't know the whole story I don't know everybody involved I don't know and I just I don't feel like I have the right um to start giving out counseling via email and I think it sets a dangerous precedent and so it's not it's not a question of I don't care about your situation it's a question of I question my ability and my right given that circumstances to start handing out personal advice and and um personal counsel and so it's to protect you from my own Folly and failings and foolishness is to protect you from a complete stranger not knowing the entire situation giving you the wrong kind of advice okay I hope you understand that and I hope that makes sense um the other thing is the sheer volume that comes in if I started doing that that would be eight to ten hours a day for the rest of my life just sitting there answering these emails and",
    "language": "en",
    "start_seconds": 0.0,
    "end_seconds": 347.0,
    "timestamp_url": "",
    "category": "",
    "tags": [],
    "views": 0,
    "published_at": null,
    "chunk_index": 0,
    "previous_chunk_id": null,
    "next_chunk_id": "40b4b894-4afd-48e8-8a59-067e5c5ffc40"
  },
  {
    "chunk_id": "40b4b894-4afd-48e8-8a59-067e5c5ffc40",
    "video_id": "Att8P0C40FU",
    "channel_id": "",
    "channel_name": "Dry Creek Wrangler School",
    "title": "Heartbreak and Loss",
    "text": "I hope you understand that and I hope that makes sense um the other thing is the sheer volume that comes in if I started doing that that would be eight to ten hours a day for the rest of my life just sitting there answering these emails and that's that's not who I am okay it's not it's not it's just not who I am okay and but I do read them and and I do care and uh and there's times when I'll stop and it'll be so heavy and I'll feel such a burden I will pray and you know I'll pray over it and I'll pray for you I know some of you that doesn't mean anything to you but I at least want you to know that I do read everything comes in and I do care but I'm not the guy I'm not the guy who can start counseling and giving this stuff out okay and and so I almost feel like I need to apologize for not being that guy but that's why um but I can give some just some general what I do I can just give some general opinions and viewpoints on life on things that I have been through um you know so guys get on here and they say you know I have been and and ladies too I have been looking for love for years and it's just been one crash after another and I keep looking and I keep searching and I keep trying to find that right one and I can't find that right one and then others get on here and say I thought I had the right one we were together for three years and and uh and then suddenly they they upped and left or or whatever and I'm heartbroken and I can't seem to get over it um my view my take on this is first off on the one side of things stop searching stop looking okay um you don't find love okay you don't find love it's not something you go out and search for you don't you're not hunting deer you're not hunting an elk you're not hunting a spouse you're working on yourself and becoming the spouse maybe that somebody else would be hunting for and then when when it's right the right people meet now that sounds so trite but I'm telling you I'm telling you that if",
    "language": "en",
    "start_seconds": 0.0,
    "end_seconds": 377.0,
    "timestamp_url": "",
    "category": "",
    "tags": [],
    "views": 0,
    "published_at": null,
    "chunk_index": 1,
    "previous_chunk_id": "5c31cb75-c53e-4445-86c0-057bd5c9a4fc",
    "next_chunk_id": "9bd0d3ee-c324-46ef-960e-cf2619b566eb"
  },
  {
    "chunk_id": "9bd0d3ee-c324-46ef-960e-cf2619b566eb",
    "video_id": "Att8P0C40FU",
    "channel_id": "",
    "channel_name": "Dry Creek Wrangler School",
    "title": "Heartbreak and Loss",
    "text": "e not hunting a spouse you're working on yourself and becoming the spouse maybe that somebody else would be hunting for and then when when it's right the right people meet now that sounds so trite but I'm telling you I'm telling you that if you feel like I'm walking in deep water here if if you search for something hard enough you will convince yourself that you have found what you're searching for if you look for a flaw in a person this is an illustration if you look for a flaw in a person if you look hard enough you'll find it all right if you've been hurt in church if you've been hurt in religion if you've been hurt by pastors or whatever before and you meet a new pastor doesn't matter how good he is if you search hard enough you will find something in that person that you can be offended at well it's the same thing if you search hard enough for that love of your life you'll find it but it won't be it okay I don't know if I can make that make sense you want to find that mate you want to find it so hard that you will create in your mind you will form them in your mind to what you want them to be because you're searching so hard um but if you stop searching number one you'll stop the frustration all right you'll stop the frustration and you'll find peace and until and I've mentioned this in video before until you find peace in Who You Are um you cannot get that peace from somebody else all right if you're gonna if you're going to find a soul mate you guys are going to be brought together it's going to happen and if it doesn't happen that way it's not something you want that's why it keeps it keeps failing it keeps breaking because you want it so bad that you will search so hard that when you meet someone you will desperately check off all the boxes that meet what you're looking for and you will desperately ignore all the boxes that are what you don't need because you're searching too hard all right um so that's my recommendation to those who are looking for a mate who are looking for that looking for that person um stop looking it's it's a it's a sorry it's a sorry example but how many of you have torn your house apart looking for the remote control and didn't find it when you stop looking and go to Walmart and buy you another universal remote control you'll find the old one when you stop looking okay it's a poor example poor illustration but um chew on it think about it meditate on it look back over your life and I think maybe you'll see a little nugget there that might help you on the other side of things I I can't speak I can't speak too familiarly with that subject um both my parents are are still alive all my siblings are still alive um I I have I've never lost to death anyone that I was really close to my grandparents I was pallbearer at my grandfather's funeral when I was 14 on my 14th birthday but my mother was a baby of 12 kids and so by the time I came along there were so many grandkids running around I was just another number uh yelling through the house my grandfather had had a stroke he couldn't speak I never heard my grandfather say a word never heard him speak and uh you know I know you know I knew I was loved and everything but I was just another number and when my grandparents on my mom's side passed uh I wasn't close to them so there wasn't that devastating loss that heartbreak if if that makes sense but I have I have had loss and I have had heartbreak um and is so trite but this too shall pass okay it will pass time does heal all wounds now it doesn't seem like it for you right now um but in the meantime what what would I advise what do I suggest I suggest you move on I suggest you move on um some of you have lost a girlfriend that you were thought was the one and they're gone and you still have her picture on your phone I bet money you still have her her number in your phone uh you still have things around the house um just Yesterday's Gone just Purge it and move on and it's like it's like a wound it's like a cut all right it'll start scabbing over but we'll just keep ripping that scab off we'll keep picking that scab off we'll just keep on and so it doesn't heal all right it's not easy I know and it hurts I know and it seems like you'll never get over it that loss the loss of of your mom the loss of your your grandfather the loss of a best friend that got killed in a car wreck uh cherish their memory cherish their memory and honor their memory but keep going on with life and just keep moving forward and and in time and in time it'll ease it does I know it seems such shallow trite easy advice but it's just a way of humanity it's a way of mankind it's been like this since man began death is as much a part of life as life itself you cannot have one without the other all right so just it's not much help but there it is and I hope it helps a little bit okay A couple of things the uh I've been asked and pleaded with and begged and hammered and nagged and cajoled for months now and so I have finally pulled the trigger uh I started a podcast and so it's the guy who's doing it I don't know nothing about it okay I just provide content send it to the guy that's smarter me and he said just tell you that anywhere that you normally listen to podcasts whether Spotify or apple podcast or wherever you can find it on there it's Dry Creek Wrangler and so we've taken the uh We've started taking the videos that will lend itself to that and pulling the audio off and posting them and so you'll recognize some of the titles and then I've started recording new stuff that is just specifically for the podcast and we're going to see how that see how that goes and so don't ever let it be said that you can't teach an old dog new tricks because this old dog has learned a lot of new tricks in the last year okay so it's there is a podcast Dry Creek Wrangler wherever you go to watch podcast I don't know don't forget Mama's Channel Dry Creek mama if you haven't checked that out yet and uh oh let's see patreon account we do have a patreon account for those who are wanting to support what we're trying to do here and trying to build and uh what is the cigar just because I know if I don't say it you're going to ask and some of you are going to ask anyhow I never I don't think in all of the videos I've put out I never have a cigar or a pipe but somewhere in the video I don't say what it is it's so funny I'll I'll post a video and somebody get on and say hey man what's that cigar you're smoking I won't even answer that just tells me they didn't watch the whole video okay this is a this is an Oliva V milanio Maduro it's box pressed it's a uh it's a very robust very dark Rich robust cigar with a lot of flavor and a lot of nuances to it it's not one that I have all the time but sometimes when I'm wanting that that uh that intense extra um with a lot of flavor I'll pull one of these out um it's not just super strong like a um a um who makes the what am I trying to think of mine just went blank cigar guys know like the Vengeance who makes the vengeance um well it starts with a k I'm having a I'm having a senior moment here um Kristoff thank you I say thank you thank you to myself Mama's like I don't know the Kristoff Vengeance you know some of those are they're just um they're just strong for the sake of being strong to me but this is this is not like that and so uh these part of the cigars that was sent to me by cigar place dot Biz there are sponsor on here and that's where if I order online cigars that's where I get them all now and I've had some of you have contacted me back said man I I checked those guys out and they did me really well uh they sent they were good priced shipping was really quick and they were boxed well and they're a good bunch of guys they take good care of me and so I want to want to put that out there and um I think that's about it so I just time man time okay um click like if you like it subscribe if you haven't hit that Bell so you're notified when I put something else out and if you know somebody that's going through a bit of a heartbreak right now or somebody who's frustrated because they cannot find that mate they're looking for and you say you know what that might help them then just click share and send it on over to them and we'll catch you guys next time",
    "language": "en",
    "start_seconds": 347.0,
    "end_seconds": 377.0,
    "timestamp_url": "",
    "category": "",
    "tags": [],
    "views": 0,
    "published_at": null,
    "chunk_index": 2,
    "previous_chunk_id": "40b4b894-4afd-48e8-8a59-067e5c5ffc40",
    "next_chunk_id": null
  }
]