[
  {
    "chunk_id": "554f5ff1-9e37-433d-8593-98fc5c6d328e",
    "video_id": "tAsH_LXT9P0",
    "channel_id": "",
    "channel_name": "The School of Life",
    "title": "How to Get Over Someone",
    "text": "We tend to be generous towards people who can't get over someone. It sounds romantic, if a little sad. The love affair happened a year ago but still the ex's thought remain loyal\nto every detail of the story. Maybe they've moved to another country. Perhaps they've married someone else. Maybe, they're dead.\nNone of it matters. The most famous fictional love affair\nof the 18th century Goethe's Sorrows of Young Werther is a hugely sympathetic study\nof this kind of romantic fixation. The hero, Werther,\nan ardent young student falls passionately in love with a charming and beautiful woman\nnamed Charlotte. She likes him but\ndoesn't love him back in part because\nshe's married to someone else. There are plenty of\nother nice women who single, attractive,\nand interested in Werther. But, he has no time for them. The only one he cares for\nis Charlotte. The one who doesn't care\nfor him. Eventually, unable to have\nCharlotte's love Werther decides to kill\nhimself. The novel proved\nhugely charming to its original audiences. Who praised it for its deep \nand pure understanding of love This sort of unrequited passion so often celebrated in literature\nand society more generally may sound generous,\nand in that sense, loving, but, a devotion to\nan unrequited situation is in truth, a clever way\nof ensuring that we won't end up in a relationship at all. That we won't ever need to suffer\nthe realities of love. Fixation on an absent other allows us to be publicly\ncommitted to love while privately sheltered\nfrom any of its more arduous demands. The fear of love maybe \nmotivated by a range of factors A squeamishness around hope, a self-hatred which makes\nsomeone else's love feel eerie, or a fear of self revelation\nwhich breeds a reluctance to let anyone into\nthe secret part of ourselves. The fears are serious\nand deserve sympathy. But they are generally not the issues that the romanticly fixated person ever wants to discuss. They prefer to keep the spotlight\non the unresponsive ex, rather than on their motives for continuing to dwell on them. The way to unfixate\nis not to tell ourselves that we never like the person. It's to get very serious and specific\nabout what the attraction was based on. And then to come to see that \nthe",
    "language": "en",
    "start_seconds": 1.0,
    "end_seconds": 31.0,
    "timestamp_url": "",
    "category": "",
    "tags": [],
    "views": 0,
    "published_at": null,
    "chunk_index": 0,
    "previous_chunk_id": null,
    "next_chunk_id": "e20a66e3-3cd8-4979-b29d-ebcb6bc46add"
  },
  {
    "chunk_id": "e20a66e3-3cd8-4979-b29d-ebcb6bc46add",
    "video_id": "tAsH_LXT9P0",
    "channel_id": "",
    "channel_name": "The School of Life",
    "title": "How to Get Over Someone",
    "text": "an on their motives for continuing to dwell on them. The way to unfixate\nis not to tell ourselves that we never like the person. It's to get very serious and specific\nabout what the attraction was based on. And then to come to see that \nthe qualities we had admired in the ex must necessarily exist\nin the other people who don't have the set of problems\nthat make the original relationship impossible. The careful investigation\nof the character of one person, paradoxically but very liberatingly shows that we could in fact,\nalso love someone else. This is not an exercise in getting us \nto give up on what we really want. The liberating move is to see that what we want has to exist\nin places beyond the pain enducing character we originally identified it in. We should gently recognize\nthat being dissapointed and abandoned has its curious satisfactions. It is in an emotional sense, a very safe position to be in indeed. Yet true love isn't to be acquitted\nwith pining for an absent figure. It means daring to engage\nwith a truely frightening prospect. A person who is available\nand thinks despite our strong background\nsupposition to the contrary that we're really\nrather nice. That is perhaps,\nthe only sort of challenge that properly deserve\nthe lyrical and grand word ROMANTIC.",
    "language": "en",
    "start_seconds": 1.0,
    "end_seconds": 31.0,
    "timestamp_url": "",
    "category": "",
    "tags": [],
    "views": 0,
    "published_at": null,
    "chunk_index": 1,
    "previous_chunk_id": "554f5ff1-9e37-433d-8593-98fc5c6d328e",
    "next_chunk_id": null
  }
]